<dcrgraph title="DCR Form Yes No" dataTypesStatus="show"  filterLevel="-1" zoomLevel="0" formGroupStyle="Normal" formLayoutStyle="Horizontal" graphBG="#EBEBEB"><specification><resources><events><event id="Decision"><custom><visualization><location xLoc="325" yLoc="50" /><colors bg="#f9f7ed" textStroke="#000000" stroke="#cccccc" /></visualization><roles><role>User</role></roles><groups><group /></groups><phases><phase /></phases><eventType></eventType><eventScope>private</eventScope><eventTypeData></eventTypeData><eventDescription></eventDescription><level>1</level><sequence>1</sequence><costs>0</costs><eventData><dataType sequence="1" width="small" placeholder="" hinttext="" dataSetList="">choice</dataType><dictionary><item key="Yes " value="1"></item><item key="No " value="0"></item></dictionary><validationRules></validationRules></eventData></custom></event></events><subProcesses></subProcesses><distribution></distribution><labels><label id="Decision" /></labels><labelMappings><labelMapping eventId="Decision" labelId="Decision"/></labelMappings><expressions></expressions><variables></variables><variableAccesses><writeAccesses /></variableAccesses><custom><keywords></keywords><roles><role description="">User</role></roles><groups></groups><phases></phases><eventTypes><eventType description="Form Button for DCR Forms">FormButton</eventType></eventTypes><eventParameters></eventParameters><graphDetails>DCR Graph</graphDetails><graphFilters><filteredGroups></filteredGroups><filteredRoles></filteredRoles><filteredPhases></filteredPhases></graphFilters><hightlighterMarkup id="HLM"></hightlighterMarkup></custom></resources><constraints><conditions></conditions><responses></responses><excludes></excludes><includes></includes><milestones></milestones><spawns></spawns></constraints></specification><runtime><custom><globalMarking></globalMarking></custom><marking><globalStore></globalStore><executed></executed><included><event id="Decision" /></included><pendingResponses></pendingResponses></marking><custom /></runtime></dcrgraph>